py_dependency_mapper-0.1.5.dist-info/METADATA
py_dependency_mapper-0.1.5.dist-info/WHEEL
py_dependency_mapper-0.1.5.dist-info/licenses/LICENSE
py_dependency_mapper/__init__.py
py_dependency_mapper/py_dependency_mapper.cpython-313-darwin.so
py_dependency_mapper-0.1.5.dist-info/RECORD
