Metadata-Version: 2.4
Name: py-dependency-mapper
Version: 0.1.5
Classifier: Development Status :: 4 - Beta
Classifier: Intended Audience :: Developers
Classifier: License :: OSI Approved :: MIT License
Classifier: Operating System :: MacOS
Classifier: Operating System :: POSIX :: Linux
Classifier: Operating System :: Microsoft :: Windows
Classifier: Programming Language :: Python
Classifier: Programming Language :: Rust
Classifier: Topic :: Software Development :: Build Tools
Classifier: Topic :: Utilities
License-File: LICENSE
Summary: A high-performance Python dependency mapping tool written in Rust, powered by the Ruff parser.
Author-email: Sebastian Hincapie <shincapiem@gmail.com>
Requires-Python: >=3.8
Project-URL: Homepage, https://github.com/Hinkapie/py-dependency-mapper
Project-URL: Repository, https://github.com/Hinkapie/py-dependency-mapper
